cute_light-0.2.2.dist-info/METADATA
cute_light-0.2.2.dist-info/WHEEL
cute_light-0.2.2.dist-info/license_files/LICENCE
cute_light.libs/libssl-ea58b819.so.3
cute_light.libs/libcrypto-dee22087.so.3
cute_light/__init__.py
cute_light/cute_light.cpython-312-x86_64-linux-gnu.so
cute_light-0.2.2.dist-info/RECORD
